testcell/__init__.py
testcell/_modidx.py
testcell/core.py
testcell/inout.py
testcell-0.0.8.dist-info/licenses/LICENSE
testcell-0.0.8.dist-info/METADATA
testcell-0.0.8.dist-info/WHEEL
testcell-0.0.8.dist-info/entry_points.txt
testcell-0.0.8.dist-info/top_level.txt
testcell-0.0.8.dist-info/RECORD
